gensphere/__init__.py
gensphere/genflow.py
gensphere/graph_builder.py
gensphere/hub.py
gensphere/utils.py
gensphere/visualizer.py
gensphere/yaml_utils.py
gensphere-0.1.9.dist-info/METADATA
gensphere-0.1.9.dist-info/WHEEL
gensphere-0.1.9.dist-info/RECORD
