Metadata-Version: 2.1
Name: gensphere
Version: 0.1.9
Summary: Build LLM applications from reusable components
License: MIT
Author: Octopus
Requires-Python: >=3.10,<4.0
Classifier: License :: OSI Approved :: MIT License
Classifier: Programming Language :: Python :: 3
Classifier: Programming Language :: Python :: 3.10
Classifier: Programming Language :: Python :: 3.11
Classifier: Programming Language :: Python :: 3.12
Classifier: Programming Language :: Python :: 3.13
Requires-Dist: Jinja2 (>=3.1.4,<4.0.0)
Requires-Dist: composio-core (>=0.5.35,<0.6.0)
Requires-Dist: composio-openai (>=0.5.35,<0.6.0)
Requires-Dist: dash (>=2.18.1,<3.0.0)
Requires-Dist: dash-cytoscape (>=1.0.2,<2.0.0)
Requires-Dist: langchain (>=0.3.4,<0.4.0)
Requires-Dist: langchain-community (>=0.3.3,<0.4.0)
Requires-Dist: networkx (>=3.4.2,<4.0.0)
Requires-Dist: openai (>=1.52.2,<2.0.0)
Requires-Dist: pydantic (>=2.9.2,<3.0.0)
Requires-Dist: python-dotenv (>=1.0.1,<2.0.0)
